odoo/addons/datev_export_xml/README.rst
odoo/addons/datev_export_xml/__init__.py
odoo/addons/datev_export_xml/__manifest__.py
odoo/addons/datev_export_xml/controllers/__init__.py
odoo/addons/datev_export_xml/controllers/main.py
odoo/addons/datev_export_xml/data/ir_cron_data.xml
odoo/addons/datev_export_xml/demo/export_data.xml
odoo/addons/datev_export_xml/i18n/datev_export_xml.pot
odoo/addons/datev_export_xml/i18n/de.po
odoo/addons/datev_export_xml/migrations/14.0.1.1.3/post-migrate.py
odoo/addons/datev_export_xml/models/__init__.py
odoo/addons/datev_export_xml/models/account_move.py
odoo/addons/datev_export_xml/models/datev_export.py
odoo/addons/datev_export_xml/models/datev_export_line.py
odoo/addons/datev_export_xml/models/datev_pdf_generator.py
odoo/addons/datev_export_xml/models/datev_xml_generator.py
odoo/addons/datev_export_xml/models/datev_zip_generator.py
odoo/addons/datev_export_xml/models/res_company.py
odoo/addons/datev_export_xml/models/res_config_settings.py
odoo/addons/datev_export_xml/readme/CONFIGURATION.rst
odoo/addons/datev_export_xml/readme/CONTRIBUTORS.rst
odoo/addons/datev_export_xml/readme/DESCRIPTION.rst
odoo/addons/datev_export_xml/readme/USAGE.rst
odoo/addons/datev_export_xml/security/groups.xml
odoo/addons/datev_export_xml/security/ir.model.access.csv
odoo/addons/datev_export_xml/security/security.xml
odoo/addons/datev_export_xml/static/description/belegtransfer_belege_hochladen.png
odoo/addons/datev_export_xml/static/description/belegtransfer_belege_hochladen_dateiauswahl.png
odoo/addons/datev_export_xml/static/description/belegtransfer_protokoll_auswahl.png
odoo/addons/datev_export_xml/static/description/belegtransfer_protokoll_details.png
odoo/addons/datev_export_xml/static/description/belegtransfer_protokoll_liste.png
odoo/addons/datev_export_xml/static/description/belegtransfer_protokoll_timestamp.png
odoo/addons/datev_export_xml/static/description/belegtransfer_verezcihnis_anlegen_2.png
odoo14_addon_datev_export_xml-14.0.1.1.4.dist-info/METADATA
odoo14_addon_datev_export_xml-14.0.1.1.4.dist-info/WHEEL
odoo14_addon_datev_export_xml-14.0.1.1.4.dist-info/top_level.txt
odoo14_addon_datev_export_xml-14.0.1.1.4.dist-info/RECORD
